response_pm_zov/__init__.py
response_pm_zov/my_code.py
response_pm_zov-0.4.dist-info/METADATA
response_pm_zov-0.4.dist-info/WHEEL
response_pm_zov-0.4.dist-info/top_level.txt
response_pm_zov-0.4.dist-info/RECORD
