Metadata-Version: 2.2
Name: response_pm_zov
Version: 0.4
Summary: zov
Home-page: https://github.com/yourusername/exam_library
Author: rqiza
Author-email: your.email@example.com
Classifier: Programming Language :: Python :: 3
Classifier: License :: OSI Approved :: MIT License
Classifier: Operating System :: OS Independent
Requires-Python: >=3.6
Dynamic: author
Dynamic: author-email
Dynamic: classifier
Dynamic: home-page
Dynamic: requires-python
Dynamic: summary
